Workbook
Name Slicer_Company: #N/A
Name Slicer_Period: #N/A

Sheet Project Summary
A1: Nike vs Adidas Retail Financial Performance Dashboard
A2: Project Goal
A3: This project compares Nike's and Adidas's FY2025 quarterly financial performance using revenue, profitability, liquidity, leverage, and cash flow metrics. The goal was to compare both companies' retail financial performance and identify business trends using Excel.
A5: Tools Used
A6: Microsoft Excel, PivotTables, PivotCharts, slicers, formulas, financial ratios, dashboard design
A8: Data Used
A9: Nike Q1–Q4 FY2025 quarterly earnings releases (fiscal year June 2024–May 2025) and Adidas Q1–Q4 2025 quarterly results (calendar year 2025). Nike reports in USD; Adidas reports in EUR. Adidas revenue is converted to USD at quarterly average EUR/USD rates so revenue can be compared directly. Margins and ratios are currency-neutral.
A11: Key Metrics Analyzed
A12: Revenue
A13: Gross Profit Margin
A14: Operating Margin
A15: Net Profit Margin
... A51: Sources: Nike quarterly earnings releases (SEC EDGAR, Form 8-K Exhibit 99.1); Adidas quarterly results releases.

Sheet Dashboard
A1: Nike vs Adidas Retail Financial Performance Dashboard
A2: Nike FY2025 (Jun 2024–May 2025) vs Adidas FY2025 (Jan–Dec 2025) | All revenue in USD millions
J3: Full-Year Summary KPIs (FY2025)
J4: Company | K4: Revenue (USD M) | L4: Gross Margin | M4: Operating Margin | N4: Net Margin | O4: OCF Margin
J5: Nike | K5: =SUMIFS(Table72[Revenue (USD M)],Table72[Company],$J5) -> 46309 | L5: =SUMIFS(Table72[Gross Profit],Table72[Company],$J5)/SUMIFS(Table72[Revenue],Table72[Company],$J5) -> 0.42734674 | M5: =SUMIFS(Table72[Operating Income/EBIT],Table72[Company],$J5)/SUMIFS(Table72[Revenue],Table72[Company],$J5) -> 0.081582414 | N5: =SUMIFS(Table72[Net Income],Table72[Company],$J5)/SUMIFS(Table72[Revenue],Table72[Company],$J5) -> 0.069511326 | O5: =SUMIFS(Table72[Operating Cash Flow],Table72[Company],$J5)/SUMIFS(Table72[Revenue],Table72[Company],$J5) -> 0.079854888
J6: Adidas | K6: =SUMIFS(Table72[Revenue (USD M)],Table72[Company],$J6) -> 28044.233 | L6: =SUMIFS(Table72[Gross Profit],Table72[Company],$J6)/SUMIFS(Table72[Revenue],Table72[Company],$J6) -> 0.51610173 | M6: =SUMIFS(Table72[Operating Income/EBIT],Table72[Company],$J6)/SUMIFS(Table72[Revenue],Table72[Company],$J6) -> 0.082866471 | N6: =SUMIFS(Table72[Net Income],Table72[Company],$J6)/SUMIFS(Table72[Revenue],Table72[Company],$J6) -> 0.055862319 | O6: =SUMIFS(Table72[Operating Cash Flow],Table72[Company],$J6)/SUMIFS(Table72[Revenue],Table72[Company],$J6) -> 0.030268832
A34: Note: Adidas revenue is converted from EUR to USD at each quarter's average EUR/USD rate (see Clean_Financials). Margins and ratios use each company's own currency, so they need no conversion. Nike's fiscal year runs June–May, so "Q1 2025" means Nike Q1 FY2025 (Jun–Aug 2024) and Adidas Q1 2025 (Jan–Mar 2025).
A36: Key Business Insights
A37: 1. Nike generated about 1.65x Adidas's revenue ($46.3B vs. $28.0B after converting Adidas to USD) and kept a stronger current ratio (about 2.2 vs. 1.3) every quarter.
A38: 2. Adidas earned higher gross margins every quarter (51.6% vs. 42.7% for the full year), showing stronger product-level profitability.
A39: 3. Nike's operating margin fell each quarter after Q2, from 11.3% to 2.7% in Q4, showing its operating profitability weakened in the second half of its fiscal year.
A40: 4. Adidas's operating cash flow margin improved every quarter, from -15.2% in Q1 to 16.9% in Q4, showing stronger cash generation from normal operations later in the year.
A41: 5. Adidas had a higher debt-to-assets ratio every quarter (about 70% vs. 63%), meaning it relies more on liabilities to finance its assets.

Sheet Clean_Financials
A1: Company | B1: Period | C1: Currency | D1: Revenue | E1: Gross Profit | F1: Operating Income/EBIT | G1: Net Income | H1: Current Assets | I1: Current Liabilities | J1: Total Assets | K1: Total Liabilities | L1: Operating Cash Flow | M1: Ending Cash
A2: Nike | B2: Q1 FY2026 | C2: USD millions | D2: 11720 | E2: 4943 | F2: 904 | G2: 727 | H2: 23898 | I2: 10911 | J2: 37334 | K2: 23866 | L2: 222 | M2: 7024
A3: Adidas | B3: Q1 2026 | C3: EUR millions | D3: 6592 | E3: 3369 | F3: 705 | G3: 487 | H3: 12280 | I3: 9088 | J3: 20454 | K3: 14105 | L3: -350 | M3: 873
A5: Company | B5: Period | C5: Currency | D5: Revenue | E5: Gross Profit | F5: Operating Income/EBIT | G5: Net Income | H5: Current Assets | I5: Current Liabilities | J5: Total Assets | K5: Total Liabilities | L5: Operating Cash Flow | M5: Ending Cash | N5: FX Rate to USD | O5: Revenue (USD M)
A6: Nike | B6: Q1 2025 | C6: USD millions | D6: 11589 | E6: 5257 | F6: 1264 | G6: 1051 | H6: 25040 | I6: 10628 | J6: 37867 | K6: 23923 | L6: 394 | M6: 8485 | N6: =IF(Table72[[#This Row],[Currency]]="EUR millions",INDEX($F$19:$F$22,MATCH(Table72[[#This Row],[Period]],$E$19:$E$22,0)),1) -> 1 | O6: =Table72[[#This Row],[Revenue]]*Table72[[#This Row],[FX Rate to USD]] -> 11589
A7: Nike | B7: Q2 2025 | C7: USD millions | D7: 12354 | E7: 5389 | F7: 1392 | G7: 1163 | H7: 24980 | I7: 11246 | J7: 37959 | K7: 23922 | L7: 1049 | M7: 7979 | N7: =IF(Table72[[#This Row],[Currency]]="EUR millions",INDEX($F$19:$F$22,MATCH(Table72[[#This Row],[Period]],$E$19:$E$22,0)),1) -> 1 | O7: =Table72[[#This Row],[Revenue]]*Table72[[#This Row],[FX Rate to USD]] -> 12354
A8: Nike | B8: Q3 2025 | C8: USD millions | D8: 11269 | E8: 4675 | F8: 826 | G8: 794 | H8: 24609 | I8: 11223 | J8: 37793 | K8: 23786 | L8: 1792 | M8: 8601 | N8: =IF(Table72[[#This Row],[Currency]]="EUR millions",INDEX($F$19:$F$22,MATCH(Table72[[#This Row],[Period]],$E$19:$E$22,0)),1) -> 1 | O8: =Table72[[#This Row],[Revenue]]*Table72[[#This Row],[FX Rate to USD]] -> 11269
A9: Nike | B9: Q4 2025 | C9: USD millions | D9: 11097 | E9: 4469 | F9: 296 | G9: 211 | H9: 23362 | I9: 10566 | J9: 36579 | K9: 23366 | L9: 463 | M9: 7464 | N9: =IF(Table72[[#This Row],[Currency]]="EUR millions",INDEX($F$19:$F$22,MATCH(Table72[[#This Row],[Period]],$E$19:$E$22,0)),1) -> 1 | O9: =Table72[[#This Row],[Revenue]]*Table72[[#This Row],[FX Rate to USD]] -> 11097
A10: Adidas | B10: Q1 2025 | C10: EUR millions | D10: 6153 | E10: 3205 | F10: 610 | G10: 429 | H10: 11521 | I10: 8942 | J10: 20091 | K10: 14004 | L10: -934 | M10: 1432 | N10: =IF(Table72[[#This Row],[Currency]]="EUR millions",INDEX($F$19:$F$22,MATCH(Table72[[#This Row],[Period]],$E$19:$E$22,0)),1) -> 1.051607 | O10: =Table72[[#This Row],[Revenue]]*Table72[[#This Row],[FX Rate to USD]] -> 6470.5379
A11: Adidas | B11: Q2 2025 | C11: EUR millions | D11: 5952 | E11: 3077 | F11: 546 | G11: 381 | H11: 11234 | I11: 8961 | J11: 19499 | K11: 13945 | L11: 18 | M11: 768 | N11: =IF(Table72[[#This Row],[Currency]]="EUR millions",INDEX($F$19:$F$22,MATCH(Table72[[#This Row],[Period]],$E$19:$E$22,0)),1) -> 1.1338023 | O11: =Table72[[#This Row],[Revenue]]*Table72[[#This Row],[FX Rate to USD]] -> 6748.3915
A12: Adidas | B12: Q3 2025 | C12: EUR millions | D12: 6630 | E12: 3435 | F12: 736 | G12: 485 | H12: 11967 | I12: 9133 | J12: 20147 | K12: 14068 | L12: 641 | M12: 1030 | N12: =IF(Table72[[#This Row],[Currency]]="EUR millions",INDEX($F$19:$F$22,MATCH(Table72[[#This Row],[Period]],$E$19:$E$22,0)),1) -> 1.169219 | O12: =Table72[[#This Row],[Revenue]]*Table72[[#This Row],[FX Rate to USD]] -> 7751.922
A13: Adidas | B13: Q4 2025 | C13: EUR millions | D13: 6076 | E13: 3088 | F13: 164 | G13: 91 | H13: 11977 | I13: 9094 | J13: 20262 | K13: 14137 | L13: 1026 | M13: 1617 | N13: =IF(Table72[[#This Row],[Currency]]="EUR millions",INDEX($F$19:$F$22,MATCH(Table72[[#This Row],[Period]],$E$19:$E$22,0)),1) -> 1.164151 | O13: =Table72[[#This Row],[Revenue]]*Table72[[#This Row],[FX Rate to USD]] -> 7073.3815
A16: EUR/USD exchange rates (used to convert Adidas revenue to USD)
A17: Inputs in blue = monthly average USD per 1 EUR. Quarterly rate = average of the three months.
A18: Month | B18: Quarter | C18: USD per EUR | E18: Quarter | F18: Avg USD per EUR
A19: Jan 2025 | B19: Q1 2025 | C19: 1.034781 | E19: Q1 2025 | F19: =AVERAGEIF($B$19:$B$30,E19,$C$19:$C$30) -> 1.051607
A20: Feb 2025 | B20: Q1 2025 | C20: 1.041182 | E20: Q2 2025 | F20: =AVERAGEIF($B$19:$B$30,E20,$C$19:$C$30) -> 1.1338023
A21: Mar 2025 | B21: Q1 2025 | C21: 1.078858 | E21: Q3 2025 | F21: =AVERAGEIF($B$19:$B$30,E21,$C$19:$C$30) -> 1.169219
A22: Apr 2025 | B22: Q2 2025 | C22: 1.122069 | E22: Q4 2025 | F22: =AVERAGEIF($B$19:$B$30,E22,$C$19:$C$30) -> 1.164151
A23: May 2025 | B23: Q2 2025 | C23: 1.12757
A24: Jun 2025 | B24: Q2 2025 | C24: 1.151768
A25: Jul 2025 | B25: Q3 2025 | C25: 1.169807
A26: Aug 2025 | B26: Q3 2025 | C26: 1.164684
A27: Sep 2025 | B27: Q3 2025 | C27: 1.173166
A28: Oct 2025 | B28: Q4 2025 | C28: 1.164811
A29: Nov 2025 | B29: Q4 2025 | C29: 1.156443
A30: Dec 2025 | B30: Q4 2025 | C30: 1.171199
A32: Data notes
A33: FX source: monthly average EUR to USD rates for 2025, x-rates.com (https://www.x-rates.com/average/?from=EUR&to=USD&amount=1&year=2025).
A34: Nike Operating Income/EBIT = EBIT as reported in Nike's quarterly earnings releases (Nike does not report an operating income line). Adidas = operating profit.
A35: Nike's fiscal year runs June–May: Nike "Q1 2025" = Q1 FY2025 (Jun–Aug 2024) through "Q4 2025" = Q4 FY2025 (Mar–May 2025). Adidas's fiscal year is the calendar year.
A36: Rows 1–3 hold the most recent quarter (Nike Q1 FY2026, Adidas Q1 2026) for reference. They are not used in the dashboard.

Sheet KPI
A1: Company | B1: Period | C1: Currency | D1: Gross Profit Margin | E1: Operating Margin | F1: Net Profit Margin | G1: Current Ratio | H1: Debt-to-Assets | I1: Operating Cash Flow Margin | J1: Cash-to-Revenue Ratio
A2: Nike | B2: Q1 2026 | C2: USD millions | D2: =Table7[[#This Row],[Gross Profit]]/Table7[[#This Row],[Revenue]] -> 0.42175768 | E2: =Table7[[#This Row],[Operating Income/EBIT]]/Table7[[#This Row],[Revenue]] -> 0.077133106 | F2: =Table7[[#This Row],[Net Income]]/Table7[[#This Row],[Revenue]] -> 0.062030717 | G2: =Table7[[#This Row],[Current Assets]]/Table7[[#This Row],[Current Liabilities]] -> 2.1902667 | H2: =Table7[[#This Row],[Total Liabilities]]/Table7[[#This Row],[Total Assets]] -> 0.63925644 | I2: =Table7[[#This Row],[Operating Cash Flow]]/Table7[[#This Row],[Revenue]] -> 0.01894198 | J2: =Table7[[#This Row],[Ending Cash]]/Table7[[#This Row],[Revenue]] -> 0.59931741
A3: Adidas | B3: Q1 2026 | C3: EUR millions | D3: =Table7[[#This Row],[Gross Profit]]/Table7[[#This Row],[Revenue]] -> 0.51107403 | E3: =Table7[[#This Row],[Operating Income/EBIT]]/Table7[[#This Row],[Revenue]] -> 0.10694782 | F3: =Table7[[#This Row],[Net Income]]/Table7[[#This Row],[Revenue]] -> 0.073877427 | G3: =Table7[[#This Row],[Current Assets]]/Table7[[#This Row],[Current Liabilities]] -> 1.3512324 | H3: =Table7[[#This Row],[Total Liabilities]]/Table7[[#This Row],[Total Assets]] -> 0.68959617 | I3: =Table7[[#This Row],[Operating Cash Flow]]/Table7[[#This Row],[Revenue]] -> -0.05309466 | J3: =Table7[[#This Row],[Ending Cash]]/Table7[[#This Row],[Revenue]] -> 0.13243325
A11: Company | B11: Period | C11: Currency | D11: Revenue | E11: Gross Profit Margin | F11: Operating Margin | G11: Net Profit Margin | H11: Current Ratio | I11: Debt-to-Assets | J11: Operating Cash Flow Margin | K11: Cash-to-Revenue Ratio
A12: Nike | B12: Q1 2025 | C12: USD millions | D12: 11589 | E12: =Clean_Financials!E6/Clean_Financials!D6 -> 0.45361981 | F12: =Clean_Financials!F6/Clean_Financials!D6 -> 0.10906894 | G12: =Clean_Financials!G6/Clean_Financials!D6 -> 0.090689447 | H12: =Clean_Financials!H6/Clean_Financials!I6 -> 2.3560406 | I12: =Clean_Financials!K6/Clean_Financials!J6 -> 0.6317638 | J12: =Clean_Financials!L6/Clean_Financials!D6 -> 0.033997756 | K12: =Clean_Financials!M6/Clean_Financials!D6 -> 0.73215981
A13: Nike | B13: Q2 2025 | C13: USD millions | D13: 12354 | E13: =Clean_Financials!E7/Clean_Financials!D7 -> 0.43621499 | F13: =Clean_Financials!F7/Clean_Financials!D7 -> 0.11267606 | G13: =Clean_Financials!G7/Clean_Financials!D7 -> 0.09413955 | H13: =Clean_Financials!H7/Clean_Financials!I7 -> 2.2212342 | I13: =Clean_Financials!K7/Clean_Financials!J7 -> 0.63020628 | J13: =Clean_Financials!L7/Clean_Financials!D7 -> 0.084911769 | K13: =Clean_Financials!M7/Clean_Financials!D7 -> 0.64586369
A14: Nike | B14: Q3 2025 | C14: USD millions | D14: 11269 | E14: =Clean_Financials!E8/Clean_Financials!D8 -> 0.41485491 | F14: =Clean_Financials!F8/Clean_Financials!D8 -> 0.073298429 | G14: =Clean_Financials!G8/Clean_Financials!D8 -> 0.070458781 | H14: =Clean_Financials!H8/Clean_Financials!I8 -> 2.1927292 | I14: =Clean_Financials!K8/Clean_Financials!J8 -> 0.62937581 | J14: =Clean_Financials!L8/Clean_Financials!D8 -> 0.15902032 | K14: =Clean_Financials!M8/Clean_Financials!D8 -> 0.7632443
A15: Nike | B15: Q4 2025 | C15: USD millions | D15: 11097 | E15: =Clean_Financials!E9/Clean_Financials!D9 -> 0.40272146 | F15: =Clean_Financials!F9/Clean_Financials!D9 -> 0.026673876 | G15: =Clean_Financials!G9/Clean_Financials!D9 -> 0.019014148 | H15: =Clean_Financials!H9/Clean_Financials!I9 -> 2.2110543 | I15: =Clean_Financials!K9/Clean_Financials!J9 -> 0.63878181 | J15: =Clean_Financials!L9/Clean_Financials!D9 -> 0.041722988 | K15: =Clean_Financials!M9/Clean_Financials!D9 -> 0.67261422
A16: Adidas | B16: Q1 2025 | C16: EUR millions | D16: 6153 | E16: =Clean_Financials!E10/Clean_Financials!D10 -> 0.52088412 | F16: =Clean_Financials!F10/Clean_Financials!D10 -> 0.099138632 | G16: =Clean_Financials!G10/Clean_Financials!D10 -> 0.069722087 | H16: =Clean_Financials!H10/Clean_Financials!I10 -> 1.2884142 | I16: =Clean_Financials!K10/Clean_Financials!J10 -> 0.69702852 | J16: =Clean_Financials!L10/Clean_Financials!D10 -> -0.15179587 | K16: =Clean_Financials!M10/Clean_Financials!D10 -> 0.232732
A17: Adidas | B17: Q2 2025 | C17: EUR millions | D17: 5952 | E17: =Clean_Financials!E11/Clean_Financials!D11 -> 0.51696909 | F17: =Clean_Financials!F11/Clean_Financials!D11 -> 0.091733871 | G17: =Clean_Financials!G11/Clean_Financials!D11 -> 0.064012097 | H17: =Clean_Financials!H11/Clean_Financials!I11 -> 1.2536547 | I17: =Clean_Financials!K11/Clean_Financials!J11 -> 0.71516488 | J17: =Clean_Financials!L11/Clean_Financials!D11 -> 0.0030241935 | K17: =Clean_Financials!M11/Clean_Financials!D11 -> 0.12903226
A18: Adidas | B18: Q3 2025 | C18: EUR millions | D18: 6630 | E18: =Clean_Financials!E12/Clean_Financials!D12 -> 0.51809955 | F18: =Clean_Financials!F12/Clean_Financials!D12 -> 0.11101056 | G18: =Clean_Financials!G12/Clean_Financials!D12 -> 0.073152338 | H18: =Clean_Financials!H12/Clean_Financials!I12 -> 1.3103033 | I18: =Clean_Financials!K12/Clean_Financials!J12 -> 0.69826773 | J18: =Clean_Financials!L12/Clean_Financials!D12 -> 0.09668175 | K18: =Clean_Financials!M12/Clean_Financials!D12 -> 0.15535445
A19: Adidas | B19: Q4 2025 | C19: EUR millions | D19: 6076 | E19: =Clean_Financials!E13/Clean_Financials!D13 -> 0.5082291 | F19: =Clean_Financials!F13/Clean_Financials!D13 -> 0.026991442 | G19: =Clean_Financials!G13/Clean_Financials!D13 -> 0.014976959 | H19: =Clean_Financials!H13/Clean_Financials!I13 -> 1.3170222 | I19: =Clean_Financials!K13/Clean_Financials!J13 -> 0.69771 | J19: =Clean_Financials!L13/Clean_Financials!D13 -> 0.16886109 | K19: =Clean_Financials!M13/Clean_Financials!D13 -> 0.26612903

Sheet Revenue Trend
A3: Sum of Revenue (USD M) | B3: Column Labels
A4: Row Labels | B4: Adidas | C4: Nike
A5: Q1 2025 | B5: 6470.5379 | C5: 11589
A6: Q2 2025 | B6: 6748.3915 | C6: 12354
A7: Q3 2025 | B7: 7751.922 | C7: 11269
A8: Q4 2025 | B8: 7073.3815 | C8: 11097

Sheet Gross Margin Trend
A3: Average of Gross Profit Margin | B3: Column Labels
A4: Row Labels | B4: Adidas | C4: Nike
A5: Q1 2025 | B5: 0.52088412 | C5: 0.45361981
A6: Q2 2025 | B6: 0.51696909 | C6: 0.43621499
A7: Q3 2025 | B7: 0.51809955 | C7: 0.41485491
A8: Q4 2025 | B8: 0.5082291 | C8: 0.40272146

Sheet Operating Margin
A3: Average of Operating Margin | B3: Column Labels
A4: Row Labels | B4: Adidas | C4: Nike
A5: Q1 2025 | B5: 0.099138632 | C5: 0.10906894
A6: Q2 2025 | B6: 0.091733871 | C6: 0.11267606
A7: Q3 2025 | B7: 0.11101056 | C7: 0.073298429
A8: Q4 2025 | B8: 0.026991442 | C8: 0.026673876

Sheet Net profit Margin Trend
A3: Average of Net Profit Margin | B3: Column Labels
A4: Row Labels | B4: Adidas | C4: Nike
A5: Q1 2025 | B5: 0.069722087 | C5: 0.090689447
A6: Q2 2025 | B6: 0.064012097 | C6: 0.09413955
A7: Q3 2025 | B7: 0.073152338 | C7: 0.070458781
A8: Q4 2025 | B8: 0.014976959 | C8: 0.019014148

Sheet Operating Cash Flow 
A3: Average of Operating Cash Flow Margin | B3: Column Labels
A4: Row Labels | B4: Adidas | C4: Nike
A5: Q1 2025 | B5: -0.15179587 | C5: 0.033997756
A6: Q2 2025 | B6: 0.0030241935 | C6: 0.084911769
A7: Q3 2025 | B7: 0.09668175 | C7: 0.15902032
A8: Q4 2025 | B8: 0.16886109 | C8: 0.041722988

Sheet Financial Health A
A3: Average of Current Ratio | B3: Column Labels
A4: Row Labels | B4: Adidas | C4: Nike
A5: Q1 2025 | B5: 1.2884142 | C5: 2.3560406
A6: Q2 2025 | B6: 1.2536547 | C6: 2.2212342
A7: Q3 2025 | B7: 1.3103033 | C7: 2.1927292
A8: Q4 2025 | B8: 1.3170222 | C8: 2.2110543

Sheet Financial Health B
A3: Average of Debt-to-Assets | B3: Column Labels
A4: Row Labels | B4: Adidas | C4: Nike
A5: Q1 2025 | B5: 0.69702852 | C5: 0.6317638
A6: Q2 2025 | B6: 0.71516488 | C6: 0.63020628
A7: Q3 2025 | B7: 0.69826773 | C7: 0.62937581
A8: Q4 2025 | B8: 0.69771 | C8: 0.63878181
